jsondler/__init__.py
jsondler/cols_dict.py
jsondler/constants.py
jsondler/dicts_list.py
jsondler/json_entry.py
jsondler/linked_dicts_list.py
jsondler/_lib/__init__.py
jsondler/_lib/general_utils.py
jsondler/json_tools/__init__.py
jsondler/json_tools/index.py
jsondler/json_tools/requests.py
jsondler/json_tools/restruct.py
jsondler/json_tools/serialization.py
jsondler/json_tools/sort.py
jsondler/pd_tools/__init__.py
jsondler/pd_tools/df_tools.py
jsondler/tests/__init__.py
jsondler/tests/test_json_tools.py
jsondler/tests/test_jsondler.py
jsondler/tests/test_lib.py
jsondler-0.0.4.dist-info/LICENSE
jsondler-0.0.4.dist-info/METADATA
jsondler-0.0.4.dist-info/WHEEL
jsondler-0.0.4.dist-info/entry_points.txt
jsondler-0.0.4.dist-info/top_level.txt
jsondler-0.0.4.dist-info/RECORD
