Metadata-Version: 2.1
Name: jsondler
Version: 0.0.4
Summary: JSON handler for Python
Home-page: https://github.com/loven-doo/jsondler
Author: Denis Moshensky
Author-email: loven7doo@gmail.com
License: UNKNOWN
Platform: UNKNOWN
Classifier: Programming Language :: Python :: 3
Classifier: License :: OSI Approved :: BSD License
Classifier: Operating System :: OS Independent
Requires-Dist: numpy (>=1.15.1)
Requires-Dist: pandas (>=0.23.4)
